{
  "hash": "b70c961ee168f16ea827361508f93a57",
  "root": "esy-bullet-ocaml@path:.",
  "node": {
    "esy-bullet-ocaml@path:.": {
      "record": {
        "name": "esy-bullet-ocaml",
        "version": "path:.",
        "source": "path:.",
        "files": [],
        "opam": null
      },
      "dependencies": [ "@bryphe/ocaml@github:bryphe/ocaml#1148fdf" ]
    },
    "@bryphe/ocaml@github:bryphe/ocaml#1148fdf": {
      "record": {
        "name": "@bryphe/ocaml",
        "version": "github:bryphe/ocaml#1148fdf",
        "source": "github:bryphe/ocaml#1148fdf",
        "files": [],
        "opam": null
      },
      "dependencies": []
    }
  }
}